{
  "1": "Tortoise",
  "3": "Magpie",
  "4": "Sea turtle",
  "5": "Football",
  "6": "Ambulance",
  "7": "Ladder",
  "8": "Toothbrush",
  "9": "Syringe",
  "10": "Sink",
  "11": "Toy",
  "12": "Organ",
  "13": "Cassette deck",
  "14": "Apple",
  "15": "Human eye",
  "16": "Cosmetics",
  "17": "Paddle",
  "18": "Snowman",
  "19": "Beer",
  "20": "Chopsticks",
  "21": "Human beard",
  "22": "Bird",
  "23": "Parking meter",
  "24": "Traffic light",
  "25": "Croissant",
  "26": "Cucumber",
  "27": "Radish",
  "28": "Towel",
  "29": "Doll",
  "30": "Skull",
  "31": "Washing machine",
  "32": "Glove",
  "33": "Tick",
  "34": "Belt",
  "35": "Sunglasses",
  "36": "Banjo",
  "37": "Cart",
  "38": "Ball",
  "39": "Backpack",
  "40": "Bicycle",
  "41": "Home appliance",
  "42": "Centipede",
  "43": "Boat",
  "44": "Surfboard",
  "45": "Boot",
  "46": "Headphones",
  "47": "Hot dog",
  "48": "Shorts",
  "49": "Fast food",
  "50": "Bus",
  "51": "Boy",
  "52": "Screwdriver",
  "53": "Bicycle wheel",
  "54": "Barge",
  "55": "Laptop",
  "56": "Miniskirt",
  "57": "Drill",
  "58": "Dress",
  "59": "Bear",
  "60": "Waffle",
  "61": "Pancake",
  "62": "Brown bear",
  "63": "Woodpecker",
  "64": "Blue jay",
  "65": "Pretzel",
  "66": "Bagel",
  "67": "Tower",
  "68": "Teapot",
  "69": "Person",
  "70": "Bow and arrow",
  "71": "Swimwear",
  "72": "Beehive",
  "73": "Brassiere",
  "74": "Bee",
  "75": "Bat",
  "76": "Starfish",
  "77": "Popcorn",
  "78": "Burrito",
  "79": "Chainsaw",
  "80": "Balloon",
  "81": "Wrench",
  "82": "Tent",
  "83": "Vehicle registration plate",
  "84": "Lantern",
  "85": "Toaster",
  "86": "Flashlight",
  "87": "Billboard",
  "88": "Tiara",
  "89": "Limousine",
  "90": "Necklace",
  "91": "Carnivore",
  "92": "Scissors",
  "93": "Stairs",
  "94": "Computer keyboard",
  "95": "Printer",
  "96": "Traffic sign",
  "97": "Chair",
  "98": "Shirt",
  "99": "Poster",
  "100": "Cheese",
  "101": "Sock",
  "102": "Fire hydrant",
  "103": "Land vehicle",
  "104": "Earrings",
  "105": "Tie",
  "106": "Watercraft",
  "107": "Cabinetry",
  "108": "Suitcase",
  "109": "Muffin",
  "110": "Bidet",
  "111": "Snack",
  "112": "Snowmobile",
  "113": "Clock",
  "114": "Medical equipment",
  "115": "Cattle",
  "116": "Cello",
  "117": "Jet ski",
  "118": "Camel",
  "119": "Coat",
  "120": "Suit",
  "121": "Desk",
  "122": "Cat",
  "123": "Bronze sculpture",
  "124": "Juice",
  "125": "Gondola",
  "126": "Beetle",
  "127": "Cannon",
  "128": "Computer mouse",
  "129": "Cookie",
  "130": "Office building",
  "131": "Fountain",
  "132": "Coin",
  "133": "Calculator",
  "134": "Cocktail",
  "135": "Computer monitor",
  "136": "Box",
  "137": "Stapler",
  "138": "Christmas tree",
  "139": "Cowboy hat",
  "140": "Hiking equipment",
  "141": "Studio couch",
  "142": "Drum",
  "143": "Dessert",
  "144": "Wine rack",
  "145": "Drink",
  "146": "Zucchini",
  "148": "Human mouth",
  "149": "Dairy",
  "150": "Dice",
  "151": "Oven",
  "152": "Dinosaur",
  "153": "Ratchet",
  "154": "Couch",
  "155": "Cricket ball",
  "156": "Winter melon",
  "157": "Spatula",
  "158": "Whiteboard",
  "160": "Door",
  "161": "Hat",
  "162": "Shower",
  "163": "Eraser",
  "164": "Fedora",
  "165": "Guacamole",
  "166": "Dagger",
  "167": "Scarf",
  "168": "Dolphin",
  "169": "Sombrero",
  "170": "Tin can",
  "171": "Mug",
  "172": "Tap",
  "173": "Harbor seal",
  "174": "Stretcher",
  "175": "Can opener",
  "176": "Goggles",
  "177": "Human body",
  "178": "Roller skates",
  "179": "Coffee cup",
  "180": "Cutting board",
  "181": "Blender",
  "182": "Plumbing fixture",
  "183": "Stop sign",
  "184": "Office supplies",
  "185": "Volleyball",
  "186": "Vase",
  "187": "Slow cooker",
  "188": "Wardrobe",
  "189": "Coffee",
  "190": "Whisk",
  "191": "Paper towel",
  "192": "Personal care",
  "193": "Food",
  "194": "Sun hat",
  "195": "Tree house",
  "196": "Flying disc",
  "197": "Skirt",
  "198": "Gas stove",
  "199": "Salt and pepper shakers",
  "200": "Mechanical fan",
  "201": "Face powder",
  "202": "Fax",
  "203": "Fruit",
  "204": "French fries",
  "205": "Nightstand",
  "206": "Barrel",
  "207": "Kite",
  "208": "Tart",
  "209": "Treadmill",
  "210": "Fox",
  "211": "Flag",
  "212": "Horn",
  "213": "Window blind",
  "214": "Human foot",
  "215": "Golf cart",
  "216": "Jacket",
  "217": "Egg",
  "218": "Street light",
  "219": "Guitar",
  "220": "Pillow",
  "221": "Human leg",
  "222": "Isopod",
  "223": "Grape",
  "224": "Human ear",
  "225": "Power plugs and sockets",
  "226": "Panda",
  "227": "Giraffe",
  "228": "Woman",
  "229": "Door handle",
  "230": "Rhinoceros",
  "231": "Bathtub",
  "232": "Goldfish",
  "233": "Houseplant",
  "234": "Goat",
  "235": "Baseball bat",
  "236": "Baseball glove",
  "237": "Mixing bowl",
  "238": "Marine invertebrates",
  "239": "Kitchen utensil",
  "240": "Light switch",
  "241": "House",
  "242": "Horse",
  "243": "Stationary bicycle",
  "244": "Hammer",
  "245": "Ceiling fan",
  "246": "Sofa bed",
  "247": "Adhesive tape",
  "248": "Harp",
  "249": "Sandal",
  "250": "Bicycle helmet",
  "251": "Saucer",
  "252": "Harpsichord",
  "253": "Human hair",
  "254": "Heater",
  "256": "Hamster",
  "257": "Curtain",
  "258": "Bed",
  "259": "Kettle",
  "260": "Fireplace",
  "261": "Scale",
  "262": "Drinking straw",
  "263": "Insect",
  "264": "Hair dryer",
  "267": "Invertebrate",
  "268": "Food processor",
  "269": "Bookcase",
  "270": "Refrigerator",
  "271": "Wood-burning stove",
  "272": "Punching bag",
  "273": "Common fig",
  "274": "Cocktail shaker",
  "275": "Jaguar",
  "276": "Golf ball",
  "277": "Fashion accessory",
  "278": "Alarm clock",
  "279": "Filing cabinet",
  "280": "Artichoke",
  "281": "Table",
  "282": "Tableware",
  "283": "Kangaroo",
  "284": "Koala",
  "285": "Knife",
  "286": "Bottle",
  "287": "Bottle opener",
  "288": "Lynx",
  "289": "Lavender",
  "290": "Lighthouse",
  "291": "Dumbbell",
  "292": "Human head",
  "293": "Bowl",
  "294": "Humidifier",
  "295": "Porch",
  "296": "Lizard",
  "297": "Billiard table",
  "298": "Mammal",
  "299": "Mouse",
  "300": "Motorcycle",
  "301": "Musical instrument",
  "302": "Swim cap",
  "303": "Frying pan",
  "304": "Snowplow",
  "305": "Bathroom cabinet",
  "306": "Missile",
  "307": "Bust",
  "308": "Man",
  "309": "Waffle iron",
  "310": "Milk",
  "311": "Ring binder",
  "312": "Plate",
  "313": "Mobile phone",
  "314": "Baked goods",
  "315": "Mushroom",
  "317": "Pitcher",
  "318": "Mirror",
  "319": "Lifejacket",
  "320": "Table tennis racket",
  "321": "Pencil case",
  "322": "Musical keyboard",
  "323": "Scoreboard",
  "324": "Briefcase",
  "325": "Kitchen knife",
  "326": "Nail",
  "327": "Tennis ball",
  "328": "Plastic bag",
  "329": "Oboe",
  "330": "Chest of drawers",
  "331": "Ostrich",
  "332": "Piano",
  "333": "Girl",
  "334": "Plant",
  "335": "Potato",
  "337": "Sports equipment",
  "338": "Pasta",
  "339": "Penguin",
  "340": "Pumpkin",
  "341": "Pear",
  "342": "Infant bed",
  "343": "Polar bear",
  "344": "Mixer",
  "345": "Cupboard",
  "346": "Jacuzzi",
  "347": "Pizza",
  "348": "Digital clock",
  "349": "Pig",
  "350": "Reptile",
  "351": "Rifle",
  "352": "Lipstick",
  "353": "Skateboard",
  "354": "Raven",
  "355": "High heels",
  "356": "Red panda",
  "357": "Rose",
  "358": "Rabbit",
  "359": "Sculpture",
  "360": "Saxophone",
  "361": "Shotgun",
  "362": "Seafood",
  "363": "Submarine sandwich",
  "364": "Snowboard",
  "365": "Sword",
  "366": "Picture frame",
  "367": "Sushi",
  "368": "Loveseat",
  "369": "Ski",
  "370": "Squirrel",
  "371": "Tripod",
  "372": "Stethoscope",
  "373": "Submarine",
  "374": "Scorpion",
  "375": "Segway",
  "376": "Training bench",
  "377": "Snake",
  "378": "Coffee table",
  "379": "Skyscraper",
  "380": "Sheep",
  "381": "Television",
  "382": "Trombone",
  "383": "Tea",
  "384": "Tank",
  "385": "Taco",
  "386": "Telephone",
  "388": "Tiger",
  "389": "Strawberry",
  "390": "Trumpet",
  "391": "Tree",
  "392": "Tomato",
  "393": "Train",
  "394": "Tool",
  "395": "Picnic basket",
  "397": "Trousers",
  "398": "Bowling equipment",
  "399": "Football helmet",
  "400": "Truck",
  "401": "Measuring cup",
  "402": "Coffeemaker",
  "403": "Violin",
  "404": "Vehicle",
  "405": "Handbag",
  "407": "Wine",
  "408": "Weapon",
  "409": "Wheel",
  "410": "Worm",
  "411": "Wok",
  "412": "Whale",
  "413": "Zebra",
  "414": "Auto part",
  "415": "Jug",
  "417": "Cream",
  "418": "Monkey",
  "419": "Lion",
  "420": "Bread",
  "421": "Platter",
  "422": "Chicken",
  "423": "Eagle",
  "424": "Helicopter",
  "425": "Owl",
  "426": "Duck",
  "427": "Turtle",
  "428": "Hippopotamus",
  "429": "Crocodile",
  "430": "Toilet",
  "431": "Toilet paper",
  "432": "Squid",
  "433": "Clothing",
  "434": "Footwear",
  "435": "Lemon",
  "436": "Spider",
  "437": "Deer",
  "438": "Frog",
  "439": "Banana",
  "440": "Rocket",
  "441": "Wine glass",
  "442": "Countertop",
  "443": "Tablet computer",
  "444": "Waste container",
  "445": "Swimming pool",
  "446": "Dog",
  "447": "Book",
  "448": "Elephant",
  "449": "Shark",
  "450": "Candle",
  "451": "Leopard",
  "452": "Axe",
  "453": "Hand dryer",
  "454": "Soap dispenser",
  "455": "Porcupine",
  "456": "Flower",
  "457": "Canary",
  "458": "Cheetah",
  "459": "Palm tree",
  "460": "Hamburger",
  "461": "Maple",
  "462": "Building",
  "463": "Fish",
  "464": "Lobster",
  "465": "Asparagus",
  "466": "Furniture",
  "467": "Hedgehog",
  "468": "Airplane",
  "469": "Spoon",
  "470": "Otter",
  "471": "Bull",
  "472": "Oyster",
  "473": "Horizontal bar",
  "474": "Convenience store",
  "476": "Bench",
  "477": "Ice cream",
  "478": "Caterpillar",
  "479": "Butterfly",
  "480": "Parachute",
  "481": "Orange",
  "482": "Antelope",
  "483": "Beaker",
  "484": "Moths and butterflies",
  "485": "Window",
  "486": "Closet",
  "487": "Castle",
  "488": "Jellyfish",
  "489": "Goose",
  "490": "Mule",
  "491": "Swan",
  "492": "Peach",
  "493": "Coconut",
  "494": "Seat belt",
  "495": "Raccoon",
  "496": "Chisel",
  "497": "Fork",
  "498": "Lamp",
  "499": "Camera",
  "500": "Squash",
  "501": "Racket",
  "502": "Human face",
  "503": "Human arm",
  "504": "Vegetable",
  "505": "Diaper",
  "506": "Unicycle",
  "507": "Falcon",
  "509": "Snail",
  "510": "Shellfish",
  "511": "Cabbage",
  "512": "Carrot",
  "513": "Mango",
  "514": "Jeans",
  "515": "Flowerpot",
  "516": "Pineapple",
  "517": "Drawer",
  "518": "Stool",
  "519": "Envelope",
  "520": "Cake",
  "521": "Dragonfly",
  "522": "Sunflower",
  "523": "Microwave oven",
  "524": "Honeycomb",
  "525": "Marine mammal",
  "526": "Sea lion",
  "527": "Ladybug",
  "528": "Shelf",
  "529": "Watch",
  "530": "Candy",
  "531": "Salad",
  "532": "Parrot",
  "533": "Handgun",
  "534": "Sparrow",
  "535": "Van",
  "537": "Spice rack",
  "538": "Light bulb",
  "539": "Corded phone",
  "540": "Sports uniform",
  "541": "Tennis racket",
  "542": "Wall clock",
  "543": "Serving tray",
  "544": "Kitchen & dining room table",
  "545": "Dog bed",
  "546": "Cake stand",
  "547": "Cat furniture",
  "548": "Bathroom accessory",
  "551": "Kitchen appliance",
  "552": "Tire",
  "553": "Ruler",
  "554": "Luggage and bags",
  "555": "Microphone",
  "556": "Broccoli",
  "557": "Umbrella",
  "558": "Pastry",
  "559": "Grapefruit",
  "561": "Animal",
  "562": "Bell pepper",
  "563": "Turkey",
  "564": "Lily",
  "565": "Pomegranate",
  "566": "Doughnut",
  "567": "Glasses",
  "568": "Human nose",
  "569": "Pen",
  "570": "Ant",
  "571": "Car",
  "572": "Aircraft",
  "573": "Human hand",
  "574": "Skunk",
  "575": "Teddy bear",
  "576": "Watermelon",
  "577": "Cantaloupe",
  "578": "Dishwasher",
  "579": "Flute",
  "580": "Balance beam",
  "581": "Sandwich",
  "582": "Shrimp",
  "583": "Sewing machine",
  "584": "Binoculars",
  "585": "Rays and skates",
  "586": "Ipod",
  "587": "Accordion",
  "588": "Willow",
  "589": "Crab",
  "590": "Crown",
  "591": "Seahorse",
  "592": "Perfume",
  "593": "Alpaca",
  "594": "Taxi",
  "595": "Canoe",
  "596": "Remote control",
  "597": "Wheelchair",
  "598": "Rugby ball",
  "599": "Armadillo",
  "601": "Helmet"
}